sp2p/__init__.py
sp2p/client.py
sp2p/client2.py
sp2p/library.py
sp2p/server.py
sp2ppy-1.0.0.dist-info/METADATA
sp2ppy-1.0.0.dist-info/WHEEL
sp2ppy-1.0.0.dist-info/top_level.txt
sp2ppy-1.0.0.dist-info/RECORD
