Metadata-Version: 2.4
Name: sp2ppy
Version: 1.0.0
Summary: Super P2P library
Author-email: Arigadam <oficalkapudovo@gmail.com>
License-Expression: MIT
Classifier: Programming Language :: Python :: 3
Classifier: Operating System :: OS Independent
Requires-Python: >=3.9
